Metadata-Version: 2.1
Name: galileod
Version: 0.0.3.2
Summary: UNKNOWN
Home-page: UNKNOWN
License: UNKNOWN
Platform: UNKNOWN
Requires-Python: >=3.6.7
Requires-Dist: flask (>=1.0.2)
Requires-Dist: flask-cors (>=3.0.7)
Requires-Dist: pysha3 (>=0.2.1)
Requires-Dist: docker (>=3.7.0)
Requires-Dist: requests (>=2.21.0)
Requires-Dist: pycryptodome (>=3.7.3)
Requires-Dist: cryptography (>=2.6.1)
Requires-Dist: pyopenssl (>=19.0.0)
Requires-Dist: python-jose (>=3.0.1)
